README.md
setup.cfg
setup.py
pi_util.egg-info/PKG-INFO
pi_util.egg-info/SOURCES.txt
pi_util.egg-info/dependency_links.txt
pi_util.egg-info/top_level.txt
python_utility/__init__.py
python_utility/util.py